better_dict/__init__.py
better_dict/_version.py
better_dict/accessors.py
better_dict/core.py
better_dict/io.py
better_dict/py.typed
better_dict/utils.py
better_dict-0.0.1.dist-info/WHEEL
better_dict-0.0.1.dist-info/METADATA
better_dict-0.0.1.dist-info/RECORD
