Metadata-Version: 2.1
Name: better-dict
Version: 0.0.1
Summary: Python dictionary revamped.
Home-page: https://github.com/ingwersen-erik/better-dict
License: LICENSE.md
Author: Erik Ingwersen
Author-email: erik.ingwersen@br.ey.com
Requires-Python: >=3.8,<3.11
Classifier: Development Status :: 1 - Planning
Classifier: License :: Other/Proprietary License
Classifier: Programming Language :: Python :: 3
Classifier: Programming Language :: Python :: 3.8
Classifier: Programming Language :: Python :: 3.9
Classifier: Programming Language :: Python :: 3.10
Requires-Dist: black (>=21.10b0)
Requires-Dist: flake8 (>=4.0.1)
Requires-Dist: flake8-annotations (>=2.7.0,<3.0.0); python_full_version >= "3.6.2"
Requires-Dist: flake8-bandit (>=2.1.2)
Requires-Dist: flake8-bugbear (>=21.9.2)
Requires-Dist: flake8-docstrings (>=1.6.0)
Requires-Dist: flake8-rst-docstrings (>=0.2.5)
Requires-Dist: joblib (>=1.2.0,<2.0.0)
Requires-Dist: numpy (>=1.24.2,<2.0.0)
Requires-Dist: pandas (>=1.5.3,<2.0.0)
Requires-Dist: pytest (>=7.2.2,<8.0.0)
Requires-Dist: python-dotenv (>=0.19.2,<0.20.0)
Project-URL: Changelog, https://github.com/ingwersen-erik/better-dict/releases
Project-URL: Documentation, https://better-dict.readthedocs.io
Project-URL: Repository, https://github.com/ingwersen-erik/better-dict
